django_base_settings/__init__.py
django_base_settings/django_base_settings.py
django_base_settings/helpers/__init__.py
django_base_settings/helpers/helpers.py
django_base_settings-0.5.0.dist-info/LICENSE
django_base_settings-0.5.0.dist-info/METADATA
django_base_settings-0.5.0.dist-info/WHEEL
django_base_settings-0.5.0.dist-info/RECORD
