Metadata-Version: 2.1
Name: django-base-settings
Version: 0.5.0
Summary: Use Pydantic to enhance your Django application settings.
License: MIT
Author: vsakkas
Author-email: vasileios.sakkas96@gmail.com
Requires-Python: >=3.10,<4.0
Classifier: License :: OSI Approved :: MIT License
Classifier: Programming Language :: Python :: 3
Classifier: Programming Language :: Python :: 3.10
Classifier: Programming Language :: Python :: 3.11
Classifier: Programming Language :: Python :: 3.12
Requires-Dist: pydantic (>=2.8.2,<3.0.0)
Requires-Dist: pydantic-settings (>=2.3.4,<3.0.0)
